{
    "data": [
      {
        "name": "ZenFri Inc.",
        "href": "https://zenfri.ca/",
        "title": "Software Developer",
        "logo": "/headshot-alt-500x500.jpg",
        "start_date": "March 2024",
        "end_date": "October 2024",
        "description": [
            "",
            "",
            ""
        ],
        "links": []
      },
      {
        "name": "Ogoki Learning Inc.",
        "href": "https://www.ogokilearning.com/",
        "title": "Unity Developer",
        "logo": "/headshot-alt-500x500.jpg",
        "start_date": "September 2022",
        "end_date": "March 2024",
        "description": [
            "",
            "",
            ""
        ],
        "links": []
      }
    ]
  }